__init__.py
models.py
ballml-0.0.1.dist-info/LICENSE
ballml-0.0.1.dist-info/METADATA
ballml-0.0.1.dist-info/WHEEL
ballml-0.0.1.dist-info/top_level.txt
ballml-0.0.1.dist-info/RECORD
